Workbook

Sheet 1. START
B3: Is Your Business Registered? | D3: In Which Country are most of the Founders based? | F3: Who are the Founders?
F4: [Founder 1]
F5: [Founder 2]
F6: [Founder 3]
F7: [Founder 4]
B8: If your business is registered:
B9: In Which Country is it Registered | D9: [Your Business Name]
F11: We look to fund from USD 10,000 to USD 50,000, as a guide only
B12: What stage are you at in Your Business? | F12: How much are you looking to receive in funding?
C16: If Already In-Market
C17: How much revenue did you make in the last 12 months (USD)
B19: A few Useful Tips:
B20: Don't feel compelled to fill all the numerated rows or column, e.g. '1, 2, 3, 4....' or 'A, B, C, D....'. Simply fill in as many as are relevant to you
B21: For example, in the "Who are the Founders?" box above, we give the option to list 4 Founders. If you only have 2, list those two and ignore the remaining rows
B22: The default currency for this submission in USD. If you wish to change to a currency you are more familiar with, please indicate in the tab 'Pricing Benchmark'
B23: Please use the same currency throughout your submission

Sheet 2. Customer and Product
B1: Describe your Product or Service Offering?
B2: What do you call your product or service? | C2: Tell us more about your product or service | D2: What are the key features that distinguish your product/offering? | E2: "Unique Selling Proposition", meaning "What makes your product or service unique?" | F2: Who's the primary segment for your product or service? Describe them | G2: Who are your closest competitors? Describe 2-3 ways in which your offering is similar to or different from that of your competitors | H2: What is the price of your core product or service variant? How does this compare to the average price of the most similar competitors' products?
B3: Product / Service Name | C3: Description | D3: Key Features or Attributes | E3: What's your USP? | F3: Primary Segment? | G3: Competition and Alternatives | H3: Pricing

Sheet 3. Market Sizing 2
B2: For the Year Ending Dec 31,
B3: 2023 | C3: =B3+1 -> 2024 | D3: =C3+1 -> 2025 | E3: =D3+1 -> 2026 | F3: =E3+1 -> 2027
B4: START BELOW
A5: MARKET UNIVERSE (Customers) | C5: =B5*(1+C6) -> 0 | D5: =C5*(1+D6) -> 0 | E5: =D5*(1+E6) -> 0 | F5: =E5*(1+F6) -> 0
A6: Expected Growth | C6: 0 | D6: 0 | E6: 0 | F6: 0
A8: Addressable Level 1 | C8: =C9*C$5 -> 0 | D8: =D9*D$5 -> 0 | E8: =E9*E$5 -> 0 | F8: =F9*F$5 -> 0
A9: Customer Filter 1 % | C9: 0.8 | D9: 0.8 | E9: 0.8 | F9: 0.8
A11: Addressable Level 2 | C11: =C12*C8 -> 0 | D11: =D12*D8 -> 0 | E11: =E12*E8 -> 0 | F11: =F12*F8 -> 0
A12: Customer Filter 2 % | C12: 0.8 | D12: 0.8 | E12: 0.8 | F12: 0.8
A14: Addressable Level 3 | C14: =C15*C11 -> 0 | D14: =D15*D11 -> 0 | E14: =E15*E11 -> 0 | F14: =F15*F11 -> 0
A15: Customer Filter 3 % | C15: 0.8 | D15: 0.8 | E15: 0.8 | F15: 0.8
A17: Addressable Level 4 | C17: =C18*C14 -> 0 | D17: =D18*D14 -> 0 | E17: =E18*E14 -> 0 | F17: =F18*F14 -> 0
A18: Customer Filter 4 % | C18: 0.8 | D18: 0.8 | E18: 0.8 | F18: 0.8
A20: Addressable Level 5 | C20: =C21*C17 -> 0 | D20: =D21*D17 -> 0 | E20: =E21*E17 -> 0 | F20: =F21*F17 -> 0
A21: Market Adoption % | C21: 0.15 | D21: 0.2 | E21: 0.25 | F21: 0.3
A23: FINAL ADDRESSABLE MARKET SIZE | C23: =C20 -> 0 | D23: =D20 -> 0 | E23: =E20 -> 0 | F23: =F20 -> 0
A25: MARKET ASSUMPTIONS | C25: Section below helps to estimate the total addressable market
A26: Avg. Price per Offering | C26: 0 | D26: 0 | E26: 0 | F26: 0
A27: No. of Purchases per Customer/Year | C27: 0 | D27: 0 | E27: 0 | F27: 0
A28: Revenue/Customer per Year | C28: =C26*C27 -> 0 | D28: =D26*D27 -> 0 | E28: =E26*E27 -> 0 | F28: =F26*F27 -> 0
A30: Market Revenue Potential | C30: =C28*C23 -> 0 | D30: =D28*D23 -> 0 | E30: =E28*E23 -> 0 | F30: =F28*F23 -> 0
A32: YOUR COMPANY PROJECTIONS | C32: Section below helps to capture your revenue projections
A33: No. of Customers | B33: 0 | C33: 0 | D33: 0 | E33: 0 | F33: 0
A34: Avg No. of Purchases per Customer/Year | C34: 0 | D34: 0 | E34: 0 | F34: 0
A35: Your Avg Price per Purchase | C35: 0 | D35: 0 | E35: 0 | F35: 0
A36: Revenue/Customer/Year | C36: =C35*C34 -> 0 | D36: =D35*D34 -> 0 | E36: =E35*E34 -> 0 | F36: =F35*F34 -> 0
A38: Total Projected Revenue | C38: =AVERAGE(B33:C33)*C36 -> 0 | D38: =AVERAGE(C33:D33)*D36 -> 0 | E38: =AVERAGE(D33:E33)*E36 -> 0 | F38: =AVERAGE(E33:F33)*F36 -> 0

Sheet 4. Uses of Funds
B1: Currency | C1: USD
B3: Please detail below the main uses of funds for the investment amount you indicated in
B4: the "OVERVIEW" tab
B6: Cost Category | C6: Cost Item / Description | D6: Yr 1 Cost
B25: TOTAL | D25: =SUM(D7:D24) -> 0
B27: Check: this should be zero ('0') if total use of funds matches requested funding: | D27: =D25-'1. START'!F13 -> 0

Sheet 5. Team and Org.
B3: Tell Us About Your Team
C5: What role does each member occupy in your team? | D5: What have you done in the past, professionally, academically, entrepreneurially, personally? | E5: How much of team member's time will be dedicated to your business | F5: How much do you expect to pay yourselves in Year 1? | G5: When you're not trying to grow a billion dollar business, what are you doing?
B6: Key Team Member | C6: Role | D6: Background | E6: Time Commitment, Year 1 | F6: Expected Compensation, Year 1 | G6: Favorite Hobby
B7: ='1. START'!F4 -> [Founder 1]
B8: ='1. START'!F5 -> [Founder 2]
B9: ='1. START'!F6 -> [Founder 3]
B10: ='1. START'!F7 -> [Founder 4]
B11: ='1. START'!F8 -> 0
B14: What is the biggest Opportunity for and Risk to your business?
B16: Biggest Opportunity | C16: How Will Your Capture this Opportunity | E16: Biggest Risk | F16: How would you mitigate this risk?

Sheet 6. SUBMIT
B4: Visit the link below to submit your final application
B5: Only submit your application when you have filled out all the fields
B7: SUBMIT APPLICATION
B11: How to SUBMIT:
B13: 1. Copy the URL of your Google Sheet 10k2startup application in the navigation bar
B25: 2. Click on SUBMIT APPLICATION link above
B27: 3. Fill in the submission form details
B29: 4. Paste in your application URL in the 'Google Sheet Link' field
B31: 5. Click 'SUBMIT'
